[
  {
    "code":"AU",
    "title":"Австралия"
  },
  {
    "code":"AT",
    "title":"Австрия"
  },
  {
    "code":"AZ",
    "title":"Азербайджан"
  },
  {
    "code":"AX",
    "title":"Аландские острова"
  },
  {
    "code":"AL",
    "title":"Албания"
  },
  {
    "code":"DZ",
    "title":"Алжир"
  },
  {
    "code":"UM",
    "title":"Внешние малые острова (США)"
  },
  {
    "code":"VI",
    "title":"Американские Виргинские острова"
  },
  {
    "code":"AS",
    "title":"Американское Самоа"
  },
  {
    "code":"AI",
    "title":"Ангилья"
  },
  {
    "code":"AO",
    "title":"Ангола"
  },
  {
    "code":"AD",
    "title":"Андорра"
  },
  {
    "code":"AQ",
    "title":"Антарктида"
  },
  {
    "code":"AG",
    "title":"Антигуа и Барбуда"
  },
  {
    "code":"AR",
    "title":"Аргентина"
  },
  {
    "code":"AM",
    "title":"Армения"
  },
  {
    "code":"AW",
    "title":"Аруба"
  },
  {
    "code":"AF",
    "title":"Афганистан"
  },
  {
    "code":"BS",
    "title":"Багамы"
  },
  {
    "code":"BD",
    "title":"Бангладеш"
  },
  {
    "code":"BB",
    "title":"Барбадос"
  },
  {
    "code":"BH",
    "title":"Бахрейн"
  },
  {
    "code":"BZ",
    "title":"Белиз"
  },
  {
    "code":"BY",
    "title":"Белоруссия"
  },
  {
    "code":"BE",
    "title":"Бельгия"
  },
  {
    "code":"BJ",
    "title":"Бенин"
  },
  {
    "code":"BM",
    "title":"Бермуды"
  },
  {
    "code":"BG",
    "title":"Болгария"
  },
  {
    "code":"BO",
    "title":"Боливия"
  },
  {
    "code":"BA",
    "title":"Босния и Герцеговина"
  },
  {
    "code":"BW",
    "title":"Ботсвана"
  },
  {
    "code":"BR",
    "title":"Бразилия"
  },
  {
    "code":"IO",
    "title":"Британская территория в Индийском океане"
  },
  {
    "code":"VG",
    "title":"Британские Виргинские острова"
  },
  {
    "code":"BN",
    "title":"Бруней"
  },
  {
    "code":"BF",
    "title":"Буркина Фасо"
  },
  {
    "code":"BI",
    "title":"Бурунди"
  },
  {
    "code":"BT",
    "title":"Бутан"
  },
  {
    "code":"VU",
    "title":"Вануату"
  },
  {
    "code":"VA",
    "title":"Ватикан"
  },
  {
    "code":"GB",
    "title":"Великобритания"
  },
  {
    "code":"HU",
    "title":"Венгрия"
  },
  {
    "code":"VE",
    "title":"Венесуэла"
  },
  {
    "code":"TL",
    "title":"Восточный Тимор"
  },
  {
    "code":"VN",
    "title":"Вьетнам"
  },
  {
    "code":"GA",
    "title":"Габон"
  },
  {
    "code":"HT",
    "title":"Гаити"
  },
  {
    "code":"GY",
    "title":"Гайана"
  },
  {
    "code":"GM",
    "title":"Гамбия"
  },
  {
    "code":"GH",
    "title":"Гана"
  },
  {
    "code":"GP",
    "title":"Гваделупа"
  },
  {
    "code":"GT",
    "title":"Гватемала"
  },
  {
    "code":"GN",
    "title":"Гвинея"
  },
  {
    "code":"GW",
    "title":"Гвинея-Бисау"
  },
  {
    "code":"DE",
    "title":"Германия"
  },
  {
    "code":"GI",
    "title":"Гибралтар"
  },
  {
    "code":"HN",
    "title":"Гондурас"
  },
  {
    "code":"HK",
    "title":"Гонконг"
  },
  {
    "code":"GD",
    "title":"Гренада"
  },
  {
    "code":"GL",
    "title":"Гренландия"
  },
  {
    "code":"GR",
    "title":"Греция"
  },
  {
    "code":"GE",
    "title":"Грузия"
  },
  {
    "code":"GU",
    "title":"Гуам"
  },
  {
    "code":"DK",
    "title":"Дания"
  },
  {
    "code":"CD",
    "title":"ДР Конго"
  },
  {
    "code":"DJ",
    "title":"Джибути"
  },
  {
    "code":"DM",
    "title":"Доминика"
  },
  {
    "code":"DO",
    "title":"Доминиканская Республика"
  },
  {
    "code":"EU",
    "title":"Европейский союз"
  },
  {
    "code":"EG",
    "title":"Египет"
  },
  {
    "code":"ZM",
    "title":"Замбия"
  },
  {
    "code":"EH",
    "title":"Западная Сахара"
  },
  {
    "code":"ZW",
    "title":"Зимбабве"
  },
  {
    "code":"IL",
    "title":"Израиль"
  },
  {
    "code":"IN",
    "title":"Индия"
  },
  {
    "code":"ID",
    "title":"Индонезия"
  },
  {
    "code":"JO",
    "title":"Иордания"
  },
  {
    "code":"IQ",
    "title":"Ирак"
  },
  {
    "code":"IR",
    "title":"Иран"
  },
  {
    "code":"IE",
    "title":"Ирландия"
  },
  {
    "code":"IS",
    "title":"Исландия"
  },
  {
    "code":"ES",
    "title":"Испания"
  },
  {
    "code":"IT",
    "title":"Италия"
  },
  {
    "code":"YE",
    "title":"Йемен"
  },
  {
    "code":"KP",
    "title":"КНДР"
  },
  {
    "code":"CV",
    "title":"Кабо-Верде"
  },
  {
    "code":"KZ",
    "title":"Казахстан"
  },
  {
    "code":"KY",
    "title":"Каймановы острова"
  },
  {
    "code":"KH",
    "title":"Камбоджа"
  },
  {
    "code":"CM",
    "title":"Камерун"
  },
  {
    "code":"CA",
    "title":"Канада"
  },
  {
    "code":"QA",
    "title":"Катар"
  },
  {
    "code":"KE",
    "title":"Кения"
  },
  {
    "code":"CY",
    "title":"Кипр"
  },
  {
    "code":"KG",
    "title":"Киргизия"
  },
  {
    "code":"KI",
    "title":"Кирибати"
  },
  {
    "code":"CN",
    "title":"КНР"
  },
  {
    "code":"CC",
    "title":"Кокосовые острова"
  },
  {
    "code":"CO",
    "title":"Колумбия"
  },
  {
    "code":"KM",
    "title":"Коморы"
  },
  {
    "code":"CR",
    "title":"Коста-Рика"
  },
  {
    "code":"CI",
    "title":"Кот-д’Ивуар"
  },
  {
    "code":"CU",
    "title":"Куба"
  },
  {
    "code":"KW",
    "title":"Кувейт"
  },
  {
    "code":"LA",
    "title":"Лаос"
  },
  {
    "code":"LV",
    "title":"Латвия"
  },
  {
    "code":"LS",
    "title":"Лесото"
  },
  {
    "code":"LR",
    "title":"Либерия"
  },
  {
    "code":"LB",
    "title":"Ливан"
  },
  {
    "code":"LY",
    "title":"Ливия"
  },
  {
    "code":"LT",
    "title":"Литва"
  },
  {
    "code":"LI",
    "title":"Лихтенштейн"
  },
  {
    "code":"LU",
    "title":"Люксембург"
  },
  {
    "code":"MU",
    "title":"Маврикий"
  },
  {
    "code":"MR",
    "title":"Мавритания"
  },
  {
    "code":"MG",
    "title":"Мадагаскар"
  },
  {
    "code":"YT",
    "title":"Майотта"
  },
  {
    "code":"MO",
    "title":"Макао"
  },
  {
    "code":"MK",
    "title":"Республика Македония"
  },
  {
    "code":"MW",
    "title":"Малави"
  },
  {
    "code":"MY",
    "title":"Малайзия"
  },
  {
    "code":"ML",
    "title":"Мали"
  },
  {
    "code":"MV",
    "title":"Мальдивы"
  },
  {
    "code":"MT",
    "title":"Мальта"
  },
  {
    "code":"MA",
    "title":"Марокко"
  },
  {
    "code":"MQ",
    "title":"Мартиника"
  },
  {
    "code":"MH",
    "title":"Маршалловы Острова"
  },
  {
    "code":"MX",
    "title":"Мексика"
  },
  {
    "code":"MZ",
    "title":"Мозамбик"
  },
  {
    "code":"MD",
    "title":"Молдавия"
  },
  {
    "code":"MC",
    "title":"Монако"
  },
  {
    "code":"MN",
    "title":"Монголия"
  },
  {
    "code":"MS",
    "title":"Монтсеррат"
  },
  {
    "code":"MM",
    "title":"Мьянма"
  },
  {
    "code":"NA",
    "title":"Намибия"
  },
  {
    "code":"NR",
    "title":"Науру"
  },
  {
    "code":"NP",
    "title":"Непал"
  },
  {
    "code":"NE",
    "title":"Нигер"
  },
  {
    "code":"NG",
    "title":"Нигерия"
  },
  {
    "code":"AN",
    "title":"Нидерландские Антильские острова"
  },
  {
    "code":"NL",
    "title":"Нидерланды"
  },
  {
    "code":"NI",
    "title":"Никарагуа"
  },
  {
    "code":"NU",
    "title":"Ниуэ"
  },
  {
    "code":"NC",
    "title":"Новая Каледония"
  },
  {
    "code":"NZ",
    "title":"Новая Зеландия"
  },
  {
    "code":"NO",
    "title":"Норвегия"
  },
  {
    "code":"AE",
    "title":"ОАЭ"
  },
  {
    "code":"OM",
    "title":"Оман"
  },
  {
    "code":"CX",
    "title":"Остров Рождества"
  },
  {
    "code":"CK",
    "title":"Острова Кука"
  },
  {
    "code":"HM",
    "title":"Херд и Макдональд"
  },
  {
    "code":"PK",
    "title":"Пакистан"
  },
  {
    "code":"PW",
    "title":"Палау"
  },
  {
    "code":"PS",
    "title":"Палестина"
  },
  {
    "code":"PA",
    "title":"Панама"
  },
  {
    "code":"PG",
    "title":"Папуа — Новая Гвинея"
  },
  {
    "code":"PY",
    "title":"Парагвай"
  },
  {
    "code":"PE",
    "title":"Перу"
  },
  {
    "code":"PN",
    "title":"Острова Питкэрн"
  },
  {
    "code":"PL",
    "title":"Польша"
  },
  {
    "code":"PT",
    "title":"Португалия"
  },
  {
    "code":"PR",
    "title":"Пуэрто-Рико"
  },
  {
    "code":"CG",
    "title":"Республика Конго"
  },
  {
    "code":"RE",
    "title":"Реюньон"
  },
  {
    "code":"RU",
    "title":"Россия"
  },
  {
    "code":"RW",
    "title":"Руанда"
  },
  {
    "code":"RO",
    "title":"Румыния"
  },
  {
    "code":"US",
    "title":"США"
  },
  {
    "code":"SV",
    "title":"Сальвадор"
  },
  {
    "code":"WS",
    "title":"Самоа"
  },
  {
    "code":"SM",
    "title":"Сан-Марино"
  },
  {
    "code":"ST",
    "title":"Сан-Томе и Принсипи"
  },
  {
    "code":"SA",
    "title":"Саудовская Аравия"
  },
  {
    "code":"SZ",
    "title":"Свазиленд"
  },
  {
    "code":"SJ",
    "title":"Шпицберген и Ян-Майен"
  },
  {
    "code":"MP",
    "title":"Северные Марианские острова"
  },
  {
    "code":"SC",
    "title":"Сейшельские Острова"
  },
  {
    "code":"SN",
    "title":"Сенегал"
  },
  {
    "code":"VC",
    "title":"Сент-Винсент и Гренадины"
  },
  {
    "code":"KN",
    "title":"Сент-Китс и Невис"
  },
  {
    "code":"LC",
    "title":"Сент-Люсия"
  },
  {
    "code":"PM",
    "title":"Сен-Пьер и Микелон"
  },
  {
    "code":"RS",
    "title":"Сербия"
  },
  {
    "code":"CS",
    "title":"Сербия и Черногория (действовал до сентября 2006 года)"
  },
  {
    "code":"SG",
    "title":"Сингапур"
  },
  {
    "code":"SY",
    "title":"Сирия"
  },
  {
    "code":"SK",
    "title":"Словакия"
  },
  {
    "code":"SI",
    "title":"Словения"
  },
  {
    "code":"SB",
    "title":"Соломоновы Острова"
  },
  {
    "code":"SO",
    "title":"Сомали"
  },
  {
    "code":"SD",
    "title":"Судан"
  },
  {
    "code":"SR",
    "title":"Суринам"
  },
  {
    "code":"SL",
    "title":"Сьерра-Леоне"
  },
  {
    "code":"SU",
    "title":"СССР (действовал до сентября 1992 года)"
  },
  {
    "code":"TJ",
    "title":"Таджикистан"
  },
  {
    "code":"TH",
    "title":"Таиланд"
  },
  {
    "code":"TW",
    "title":"Китайская Республика"
  },
  {
    "code":"TZ",
    "title":"Танзания"
  },
  {
    "code":"TG",
    "title":"Того"
  },
  {
    "code":"TK",
    "title":"Токелау"
  },
  {
    "code":"TO",
    "title":"Тонга"
  },
  {
    "code":"TT",
    "title":"Тринидад и Тобаго"
  },
  {
    "code":"TV",
    "title":"Тувалу"
  },
  {
    "code":"TN",
    "title":"Тунис"
  },
  {
    "code":"TM",
    "title":"Туркмения"
  },
  {
    "code":"TR",
    "title":"Турция"
  },
  {
    "code":"UG",
    "title":"Уганда"
  },
  {
    "code":"UZ",
    "title":"Узбекистан"
  },
  {
    "code":"UA",
    "title":"Украина"
  },
  {
    "code":"UY",
    "title":"Уругвай"
  },
  {
    "code":"FO",
    "title":"Фарерские острова"
  },
  {
    "code":"FM",
    "title":"Микронезия"
  },
  {
    "code":"FJ",
    "title":"Фиджи"
  },
  {
    "code":"PH",
    "title":"Филиппины"
  },
  {
    "code":"FI",
    "title":"Финляндия"
  },
  {
    "code":"FK",
    "title":"Фолклендские острова"
  },
  {
    "code":"FR",
    "title":"Франция"
  },
  {
    "code":"GF",
    "title":"Французская Гвиана"
  },
  {
    "code":"PF",
    "title":"Французская Полинезия"
  },
  {
    "code":"TF",
    "title":"Французские Южные и Антарктические Территории"
  },
  {
    "code":"HR",
    "title":"Хорватия"
  },
  {
    "code":"CF",
    "title":"ЦАР"
  },
  {
    "code":"TD",
    "title":"Чад"
  },
  {
    "code":"ME",
    "title":"Черногория"
  },
  {
    "code":"CZ",
    "title":"Чехия"
  },
  {
    "code":"CL",
    "title":"Чили"
  },
  {
    "code":"CH",
    "title":"Швейцария"
  },
  {
    "code":"SE",
    "title":"Швеция"
  },
  {
    "code":"LK",
    "title":"Шри-Ланка"
  },
  {
    "code":"EC",
    "title":"Эквадор"
  },
  {
    "code":"GQ",
    "title":"Экваториальная Гвинея"
  },
  {
    "code":"ER",
    "title":"Эритрея"
  },
  {
    "code":"EE",
    "title":"Эстония"
  },
  {
    "code":"ET",
    "title":"Эфиопия"
  },
  {
    "code":"ZA",
    "title":"ЮАР"
  },
  {
    "code":"KR",
    "title":"Республика Корея"
  },
  {
    "code":"GS",
    "title":"Южная Георгия и Южные Сандвичевы острова"
  },
  {
    "code":"JM",
    "title":"Ямайка"
  },
  {
    "code":"JP",
    "title":"Япония"
  },
  {
    "code":"BV",
    "title":"Остров Буве"
  },
  {
    "code":"NF",
    "title":"Остров Норфолк"
  },
  {
    "code":"SH",
    "title":"Остров Святой Елены"
  },
  {
    "code":"TC",
    "title":"Тёркс и Кайкос"
  },
  {
    "code":"WF",
    "title":"Уоллис и Футуна"
  }
]